LICENSE
corenetworks/__init__.py
corenetworks/authenticators.py
corenetworks/client.py
corenetworks/exceptions.py
corenetworks/test/__init__.py
corenetworks/test/fixtures/__init__.py
corenetworks/test/fixtures/callback.py
corenetworks/test/unit/__init__.py
corenetworks/test/unit/test_authenticators.py
corenetworks/test/unit/test_client.py
corenetworks-0.2.1.dist-info/LICENSE
corenetworks-0.2.1.dist-info/WHEEL
corenetworks-0.2.1.dist-info/METADATA
corenetworks-0.2.1.dist-info/RECORD
