Metadata-Version: 2.1
Name: corenetworks
Version: 0.2.1
Summary: Python library for the core-networks.de DNS API.
Home-page: https://github.com/thegeeklab/corenetworks/
License: MIT
Keywords: dns,automation,nameserver,corenetworks
Author: Robert Kaussow
Author-email: mail@thegeeklab.de
Requires-Python: >=3.6.0,<4.0.0
Classifier: Development Status :: 5 - Production/Stable
Classifier: Environment :: Console
Classifier: Intended Audience :: Developers
Classifier: License :: OSI Approved :: MIT License
Classifier: Natural Language :: English
Classifier: Operating System :: POSIX
Classifier: Programming Language :: Python :: 3
Classifier: Programming Language :: Python :: 3.6
Classifier: Programming Language :: Python :: 3.7
Classifier: Programming Language :: Python :: 3.8
Classifier: Programming Language :: Python :: 3.9
Classifier: Topic :: Software Development
Requires-Dist: jsonschema (>=3.2.0,<4.0.0)
Requires-Dist: requests (>=2.25.1,<3.0.0)
Requires-Dist: six (>=1.15.0,<2.0.0)
Project-URL: Documentation, https://github.com/thegeeklab/corenetworks/
Project-URL: Repository, https://github.com/thegeeklab/corenetworks/
